token_auth_cli/__init__.py
token_auth_cli/auth.py
token_auth_cli/cli.py
token_auth_cli/commands.py
token_auth_cli/config.py
token_auth_cli/utils.py
token_auth_cli-0.2.1.dist-info/entry_points.txt
token_auth_cli-0.2.1.dist-info/WHEEL
token_auth_cli-0.2.1.dist-info/METADATA
token_auth_cli-0.2.1.dist-info/RECORD
